sl_cuttly/__init__.py
sl_cuttly/__main__.py
sl_cuttly-1.4.5.dist-info/LICENSE
sl_cuttly-1.4.5.dist-info/METADATA
sl_cuttly-1.4.5.dist-info/WHEEL
sl_cuttly-1.4.5.dist-info/entry_points.txt
sl_cuttly-1.4.5.dist-info/top_level.txt
sl_cuttly-1.4.5.dist-info/RECORD
